tetebeche/__init__.py
tetebeche/cmd.py
tetebeche-0.1.1.dist-info/entry_points.txt
tetebeche-0.1.1.dist-info/LICENSE
tetebeche-0.1.1.dist-info/WHEEL
tetebeche-0.1.1.dist-info/METADATA
tetebeche-0.1.1.dist-info/RECORD
