Metadata-Version: 2.1
Name: tetebeche
Version: 0.1.1
Summary: Script to generate a tėte-bêche book from two pdfs
License: Apache-2.0
Author: Jacob Smullyan
Author-email: smulloni@smullyan.org
Requires-Python: >=3.8,<4.0
Classifier: License :: OSI Approved :: Apache Software License
Classifier: Programming Language :: Python :: 3
Classifier: Programming Language :: Python :: 3.8
Classifier: Programming Language :: Python :: 3.9
Classifier: Programming Language :: Python :: 3.10
Requires-Dist: PyPDF2 (>=2.11.1,<3.0.0)
